{
  "tasks": [
    {
      "title": "Create Task List",
      "id": 885170,
      "message": "Create a list of all the tasks"
    },
    {
      "title": "Create New Task Form",
      "id": 221780,
      "message": "Create a form where you can create a new task"
    },
    {
      "title": "Add the ability to delete tasks",
      "id": 501016,
      "message": "Being able to delete tasks would be nice"
    },
    {
      "title": "New Task Demo",
      "id": 904806,
      "message": "What sup im a new task"
    },
    {
      "title": "This is a test title",
      "id": 139827,
      "message": "This message was created with the updated bootstrap ui"
    }
  ]
}